LICENSE
oracle_of_ammon/__init__.py
oracle_of_ammon/__main__.py
oracle_of_ammon/__version__.py
oracle_of_ammon/api/__init__.py
oracle_of_ammon/api/ammon.py
oracle_of_ammon/api/health.py
oracle_of_ammon/api/models.py
oracle_of_ammon/api/oracle.py
oracle_of_ammon/api/utils/filehandler.py
oracle_of_ammon/cli/main.py
oracle_of_ammon/data/faq.csv
oracle_of_ammon/data/faq.json
oracle_of_ammon/data/faq.tsv
oracle_of_ammon/data/faq.txt
oracle_of_ammon/data/faq.xlsx
oracle_of_ammon/data/semantic.txt
oracle_of_ammon/locust/__init__.py
oracle_of_ammon/locust/locust.py
oracle_of_ammon/tests/ammon_test.py
oracle_of_ammon/tests/oracle_test.py
oracle_of_ammon/utils/__init__.py
oracle_of_ammon/utils/logger.py
oracle_of_ammon-0.3.2.dist-info/METADATA
oracle_of_ammon-0.3.2.dist-info/entry_points.txt
oracle_of_ammon-0.3.2.dist-info/WHEEL
oracle_of_ammon-0.3.2.dist-info/LICENSE
oracle_of_ammon-0.3.2.dist-info/RECORD
