Metadata-Version: 2.1
Name: oracle-of-ammon
Version: 0.3.2
Summary: CLI tool for creating Search APIs.
Home-page: https://kmcleste.github.io/oracle-of-ammon/
License: MIT
Keywords: fastapi,haystack,search,faq,typer
Author: Kyle McLester
Author-email: kyle.mclester@gmail.com
Requires-Python: >=3.8.1,<3.11
Classifier: License :: OSI Approved :: MIT License
Classifier: Operating System :: OS Independent
Classifier: Programming Language :: Python :: 3
Classifier: Programming Language :: Python :: 3.9
Classifier: Programming Language :: Python :: 3.10
Classifier: Programming Language :: Python :: 3
Classifier: Programming Language :: Python :: 3.10
Classifier: Programming Language :: Python :: 3.9
Classifier: Topic :: Software Development :: Libraries :: Python Modules
Classifier: Typing :: Typed
Requires-Dist: aiofiles (>=22.1.0,<23.0.0)
Requires-Dist: bs4 (>=0.0.1,<0.0.2)
Requires-Dist: farm-haystack (>=1.13.0,<2.0.0)
Requires-Dist: fastapi (>=0.88.0,<0.89.0)
Requires-Dist: locust (>=2.14.0,<3.0.0)
Requires-Dist: markdown (>=3.2.1,<3.4)
Requires-Dist: openpyxl (>=3.0.10,<4.0.0)
Requires-Dist: pandas (>=1.5.2,<2.0.0)
Requires-Dist: pdf2image (>=1.16.2,<2.0.0)
Requires-Dist: psutil (>=5.9.4,<6.0.0)
Requires-Dist: pynvml (>=11.4.1,<12.0.0)
Requires-Dist: pytesseract (>=0.3.10,<0.4.0)
Requires-Dist: python-frontmatter (>=1.0.0,<2.0.0)
Requires-Dist: python-magic (>=0.4.27,<0.5.0)
Requires-Dist: python-multipart (>=0.0.5,<0.0.6)
Requires-Dist: requests (>=2.28.1,<3.0.0)
Requires-Dist: typer[all] (>=0.7.0,<0.8.0)
Requires-Dist: types-psutil (>=5.9.5.6,<6.0.0.0)
Requires-Dist: uvicorn (>=0.20.0,<0.21.0)
Project-URL: Repository, https://github.com/kmcleste/oracle-of-ammon
